npmanager
setup.py
_npmanager/__init__.py
_npmanager/classes.py
_npmanager/constants.py
_npmanager/manager.py
_npmanager/messages.py
_npmanager/packages/__init__.py
_npmanager/packages/mariadb.py
_npmanager/packages/nginx.py
_npmanager/packages/php.py
_npmanager/packages/pma.py
_npmanager/packages/pyapt.py
_npmanager/utils/__init__.py
_npmanager/utils/commandutils.py
_npmanager/utils/networkutils.py
_npmanager/utils/screen.py
npmanager.egg-info/PKG-INFO
npmanager.egg-info/SOURCES.txt
npmanager.egg-info/dependency_links.txt
npmanager.egg-info/top_level.txt