Metadata-Version: 1.1
Name: npmanager
Version: 1.0
Summary: The super easy way to install and manageNGINX, PHP and MariaDB
Home-page: https://github.com/ssut/npmanager
Author: SuHun Han (ssut)
Author-email: ssut@ssut.me
License: MIT License
Platform: UNKNOWN
Classifier: Development Status :: 5 - Production/Stable
Classifier: Intended Audience :: Developers
Classifier: Intended Audience :: System Administrators
Classifier: Intended Audience :: Manufacturing
Classifier: Intended Audience :: Information Technology
Classifier: License :: OSI Approved :: MIT License
Classifier: Operating System :: POSIX :: Linux
Classifier: Programming Language :: Python
Classifier: Programming Language :: Python :: 2
Classifier: Programming Language :: Python :: 2.7
Classifier: Programming Language :: Python :: 3
Classifier: Programming Language :: Python :: 3.3
Classifier: Programming Language :: Python :: 3.4
Classifier: Environment :: Console
Classifier: Environment :: Console :: Curses
Classifier: Topic :: System :: System Shells
Classifier: Topic :: System :: Systems Administration
